django_data_seed/__init__.py
django_data_seed/admin.py
django_data_seed/apps.py
django_data_seed/middleware.py
django_data_seed/models.py
django_data_seed/tests.py
django_data_seed/management/commands/fields.py
django_data_seed/management/commands/load_data.py
django_data_seed/management/commands/seeddata.py
django_data_seed/management/commands/utils.py
django_data_seed/migrations/0001_initial.py
django_data_seed/migrations/__init__.py
django_data_seed/sub_app_1/__init__.py
django_data_seed/sub_app_1/admin.py
django_data_seed/sub_app_1/apps.py
django_data_seed/sub_app_1/models.py
django_data_seed/sub_app_1/tests.py
django_data_seed/sub_app_1/views.py
django_data_seed/sub_app_1/migrations/0001_initial.py
django_data_seed/sub_app_1/migrations/__init__.py
django_data_seed/utils/admin_utils.py
django_data_seed/utils/app_utils.py
django_data_seed/utils/colorama_theme.py
django_data_seed/utils/constants.py
django_data_seed/utils/excluded_models.py
django_data_seed/utils/get_user.py
django_data_seed/utils/json_compare.py
django_data_seed/utils/model_property.py
django_data_seed/utils/signal_utils.py
django_data_seed/utils/thread_locals.py
django_data_seed/utils/utils.py
django_data_seed/utils/model_utils/model_properties.py
django_data_seed/utils/model_utils/utils.py
django_data_seed-0.4.2.dist-info/LICENSE
django_data_seed-0.4.2.dist-info/METADATA
django_data_seed-0.4.2.dist-info/WHEEL
django_data_seed-0.4.2.dist-info/top_level.txt
django_data_seed-0.4.2.dist-info/RECORD
